coregeist/__init__.py
coregeist/layers.py
coregeist/pytorch_transform.py
coregeist/resources/ctemplate.tpl.c
coregeist/transform.py
coregeist-0.1.5.dist-info/WHEEL
coregeist-0.1.5.dist-info/METADATA
coregeist-0.1.5.dist-info/RECORD
