Metadata-Version: 2.1
Name: coregeist
Version: 0.1.5
Summary: coregeist is a Python library to convert deep neural network models into c source code.
Author: germar
Author-email: g.schlegel@geisten.com
Requires-Python: >=3.7.12,<4.0.0
Classifier: Programming Language :: Python :: 3
Classifier: Programming Language :: Python :: 3.8
Classifier: Programming Language :: Python :: 3.9
Classifier: Programming Language :: Python :: 3.10
Requires-Dist: torch (>=1.10.0,<2.0.0)
Requires-Dist: typing-extensions (>=3.7.4.3,<4.0.0.0)
